pygolf/__init__.py
pygolf/__main__.py
pygolf/name_finder.py
pygolf/pygolfer.py
pygolf/unparser.py
pygolf/errors/__init__.py
pygolf/errors/no_names_left.py
pygolf/errors/python_2_code_detected.py
pygolf/helper/__init__.py
pygolf/helper/walker.py
pygolf/optimization_phases/__init__.py
pygolf/optimization_phases/always_apply_phase.py
pygolf/optimization_phases/phase.py
pygolf/optimization_phases/rename_phase.py
pygolf/optimizers/__init__.py
pygolf/optimizers/assign_name_optimizer.py
pygolf/optimizers/batch_optimizer.py
pygolf/optimizers/optimizer.py
pygolf/optimizers/rename_method_optimizer.py
pygolf/rules/__init__.py
pygolf/rules/astroid_rule.py
pygolf/rules/node_creator_helper.py
pygolf/rules/rules.py
pygolf/rules/version.py
test/rules/__init__.py
test/rules/helper_testkit.py
test/rules/test_rules.py
pygolf-1.0.2.dist-info/LICENSE
pygolf-1.0.2.dist-info/METADATA
pygolf-1.0.2.dist-info/WHEEL
pygolf-1.0.2.dist-info/entry_points.txt
pygolf-1.0.2.dist-info/top_level.txt
pygolf-1.0.2.dist-info/RECORD
