Metadata-Version: 2.1
Name: pygolf
Version: 1.0.2
Summary: An automatic python code shortener
Home-page: https://github.com/bluesheeptoken/PyGolf
Author: Bluesheeptoken
License: MIT
Keywords: golfcode shorten_code golf
Platform: UNKNOWN
Classifier: Development Status :: 4 - Beta
Classifier: Intended Audience :: Developers
Classifier: Topic :: Software Development :: Build Tools
Classifier: License :: OSI Approved :: MIT License
Classifier: Programming Language :: Python :: 3.6
Classifier: Programming Language :: Python :: 3.7
Classifier: Programming Language :: Python :: 3.8
Requires-Python: >=3.6, <4
Requires-Dist: argparse
Requires-Dist: astroid
Requires-Dist: pyperclip
